unisender_go_api/__init__.py
unisender_go_api/_api_methods.py
unisender_go_api/_api_types.py
unisender_go_api/_clients.py
unisender_go_api/_exceptions.py
unisender_go_api-0.3.0.dist-info/METADATA
unisender_go_api-0.3.0.dist-info/WHEEL
unisender_go_api-0.3.0.dist-info/RECORD
