Metadata-Version: 2.1
Name: unisender-go-api
Version: 0.3.0
Summary: Thin wrapper for the Unisender Go API
Home-page: https://pypi.org/project/unisender-go-api/
License: GNU GPLv3
Keywords: unisender,api,httpx,wrapper,asyncio
Author: Evgeny Evseev
Author-email: pelid80@gmail.com
Requires-Python: >=3.10,<4.0
Classifier: License :: Other/Proprietary License
Classifier: Programming Language :: Python :: 3
Classifier: Programming Language :: Python :: 3.10
Classifier: Programming Language :: Python :: 3.11
Classifier: Programming Language :: Python :: 3.12
Requires-Dist: httpx (>=0.24.1,<1)
Requires-Dist: pydantic[email] (>=1.10.8,<2)
Project-URL: Repository, https://gitlab.dvmn.org/dvmn-open-source-dev-tools/unisender-go-api
